pymemo/__init__.py
pymemo/memo_collection.py
pymemo/memo_item.py
pymemo/pymemo.py
pymemo_cache-1.1.0.dist-info/LICENSE
pymemo_cache-1.1.0.dist-info/METADATA
pymemo_cache-1.1.0.dist-info/WHEEL
pymemo_cache-1.1.0.dist-info/top_level.txt
pymemo_cache-1.1.0.dist-info/RECORD
