Metadata-Version: 2.1
Name: pymemo-cache
Version: 1.1.0
Summary: PyMemo: simple Python memoization library
License: MIT License
Project-URL: repository, https://github.com/luisclicio/pymemo
Keywords: memoization,memo,caching
Classifier: Programming Language :: Python :: 3
Requires-Python: >=3
License-File: LICENSE
